freidok_cli/cli/options.py
freidok_cli/cli/run.py
freidok_cli/client.py
freidok_cli/export.py
freidok_cli/models/base.py
freidok_cli/models/institutions.py
freidok_cli/models/publications.py
freidok_cli/modify.py
freidok_cli/templates/institutions/simple-list.html
freidok_cli/templates/institutions/simple-list.md
freidok_cli/templates/publications/simple-list.html
freidok_cli/templates/publications/simple-list.md
freidok_cli/tools/push_to_plone.py
freidok_cli/utils.py
freidok_cli/version.py
freidok_cli-1.2.1.dist-info/entry_points.txt
freidok_cli-1.2.1.dist-info/LICENSE
freidok_cli-1.2.1.dist-info/METADATA
freidok_cli-1.2.1.dist-info/WHEEL
freidok_cli-1.2.1.dist-info/RECORD
