Metadata-Version: 2.1
Name: freidok-cli
Version: 1.2.1
Summary: A command-line client for FreiDok, the publication platform of the University of Freiburg
Home-page: https://github.com/phys2/freidok-cli
License: MIT
Author: Alexander Haupt
Author-email: alexander.haupt@physiologie.uni-freiburg.de
Requires-Python: >=3.10,<4.0
Classifier: Development Status :: 5 - Production/Stable
Classifier: Environment :: Console
Classifier: License :: OSI Approved :: MIT License
Classifier: Operating System :: OS Independent
Classifier: Programming Language :: Python :: 3
Classifier: Programming Language :: Python :: 3.10
Classifier: Programming Language :: Python :: 3.11
Classifier: Programming Language :: Python :: 3.12
Requires-Dist: jinja2 (>=3.1.2,<4.0.0)
Requires-Dist: lxml (>=4.9.2,<5.0.0)
Requires-Dist: pydantic (>=1.10.12,<2.0.0)
Requires-Dist: python-dotenv (>=1.0.0,<2.0.0)
Requires-Dist: requests (>=2.28.1,<3.0.0)
Project-URL: Repository, https://github.com/phys2/freidok-cli
